{
    "input_ports": [
        {
            "is_list": false,
            "portName": "input_pose",
            "portType": "Pose"
        },
        {
            "is_list": false,
            "portName": "input_max",
            "portType": "String"
        }
    ],
    "output_ports": [
        {
            "is_list": false,
            "portName": "mode",
            "portType": "String"
        },
        {
            "is_list": false,
            "portName": "output_pose",
            "portType": "Pose"
        }
    ],
    "parameters": [
        {
            "default_val": "0.060000",
            "max": "MAX",
            "min": "MIN",
            "paraName": "value",
            "paraType": "Float"
        }
    ]
}
